LICENSE
MANIFEST.in
README.md
setup.cfg
setup.py
tap_harvest/__init__.py
tap_harvest.egg-info/PKG-INFO
tap_harvest.egg-info/SOURCES.txt
tap_harvest.egg-info/dependency_links.txt
tap_harvest.egg-info/entry_points.txt
tap_harvest.egg-info/requires.txt
tap_harvest.egg-info/top_level.txt
tap_harvest/schemas/clients.json
tap_harvest/schemas/contacts.json
tap_harvest/schemas/estimate_item_categories.json
tap_harvest/schemas/estimate_line_items.json
tap_harvest/schemas/estimate_messages.json
tap_harvest/schemas/estimates.json
tap_harvest/schemas/expense_categories.json
tap_harvest/schemas/expenses.json
tap_harvest/schemas/external_reference.json
tap_harvest/schemas/invoice_item_categories.json
tap_harvest/schemas/invoice_line_items.json
tap_harvest/schemas/invoice_messages.json
tap_harvest/schemas/invoice_payments.json
tap_harvest/schemas/invoices.json
tap_harvest/schemas/project_tasks.json
tap_harvest/schemas/project_users.json
tap_harvest/schemas/projects.json
tap_harvest/schemas/roles.json
tap_harvest/schemas/tasks.json
tap_harvest/schemas/time_entries.json
tap_harvest/schemas/time_entry_external_reference.json
tap_harvest/schemas/user_project_tasks.json
tap_harvest/schemas/user_projects.json
tap_harvest/schemas/user_roles.json
tap_harvest/schemas/users.json
tests/test_harvest_bookmarks.py
tests/test_harvest_future_date.py
tests/test_harvest_pagination.py
tests/test_harvest_start_date.py
tests/test_harvest_start_date_honoring.py